calculator_jms/__init__.py
calculator_jms/main.py
calculator_jms-0.1.0.dist-info/METADATA
calculator_jms-0.1.0.dist-info/WHEEL
calculator_jms-0.1.0.dist-info/entry_points.txt
calculator_jms-0.1.0.dist-info/RECORD
